setup.py
apigw/__init__.py
apigw/api_base.py
apigw/api_log.py
apigw/business_process.py
apigw/client.py
apigw/iam.py
apigw/oauth.py
apigw.egg-info/PKG-INFO
apigw.egg-info/SOURCES.txt
apigw.egg-info/dependency_links.txt
apigw.egg-info/requires.txt
apigw.egg-info/top_level.txt