Metadata-Version: 1.0
Name: apigw
Version: 1.0.2
Summary: NTT Communications API SDK
Home-page: https://github.com/nttcom/apigw-python-sdk
Author: NTT Communications APIGateway Teams
Author-email: apigateway@ntt.com
License: Apache License, Version 2.0
Keywords: apigw api sdk B2B
Platform: UNKNOWN
